orca_sdk/__init__.py
orca_sdk/_shared/__init__.py
orca_sdk/_shared/metrics.py
orca_sdk/_shared/metrics_test.py
orca_sdk/_utils/__init__.py
orca_sdk/_utils/analysis_ui.py
orca_sdk/_utils/analysis_ui_style.css
orca_sdk/_utils/auth.py
orca_sdk/_utils/auth_test.py
orca_sdk/_utils/common.py
orca_sdk/_utils/data_parsing.py
orca_sdk/_utils/data_parsing_disk_test.py
orca_sdk/_utils/data_parsing_torch_test.py
orca_sdk/_utils/pagination.py
orca_sdk/_utils/pagination_test.py
orca_sdk/_utils/prediction_result_ui.css
orca_sdk/_utils/prediction_result_ui.py
orca_sdk/_utils/tqdm_file_reader.py
orca_sdk/_utils/value_parser.py
orca_sdk/_utils/value_parser_test.py
orca_sdk/async_client.py
orca_sdk/classification_model.py
orca_sdk/classification_model_test.py
orca_sdk/client.py
orca_sdk/conftest.py
orca_sdk/credentials.py
orca_sdk/credentials_test.py
orca_sdk/datasource.py
orca_sdk/datasource_test.py
orca_sdk/embedding_model.py
orca_sdk/embedding_model_test.py
orca_sdk/job.py
orca_sdk/job_test.py
orca_sdk/memoryset.py
orca_sdk/memoryset_test.py
orca_sdk/regression_model.py
orca_sdk/regression_model_test.py
orca_sdk/telemetry.py
orca_sdk/telemetry_test.py
orca_sdk-0.1.11.dist-info/METADATA
orca_sdk-0.1.11.dist-info/WHEEL
orca_sdk-0.1.11.dist-info/RECORD
