Metadata-Version: 2.4
Name: orca_sdk
Version: 0.1.11
Summary: SDK for interacting with Orca Services
License-Expression: Apache-2.0
Author: Orca DB Inc.
Author-email: dev-rel@orcadb.ai
Requires-Python: >=3.11,<3.15
Classifier: Programming Language :: Python :: 3
Classifier: Programming Language :: Python :: 3.11
Classifier: Programming Language :: Python :: 3.12
Classifier: Programming Language :: Python :: 3.13
Classifier: Programming Language :: Python :: 3.14
Provides-Extra: ui
Requires-Dist: datasets (>=4.4.0,<5)
Requires-Dist: gradio (>=6.0.0,<7) ; extra == "ui"
Requires-Dist: httpx (>=0.28.1)
Requires-Dist: httpx-retries (>=0.4.3,<0.5.0)
Requires-Dist: numpy (>=2.1.0,<3)
Requires-Dist: python-dotenv (>=1.1.0)
Requires-Dist: scikit-learn (>=1.6.1,<2)
